AUTHORS
MANIFEST.in
README.md
setup.py
django_mailtestfield.egg-info/PKG-INFO
django_mailtestfield.egg-info/SOURCES.txt
django_mailtestfield.egg-info/dependency_links.txt
django_mailtestfield.egg-info/not-zip-safe
django_mailtestfield.egg-info/top_level.txt
mailtest/__init__.py
mailtest/fields.py
mailtest/validators.py