Metadata-Version: 1.1
Name: django-mailtestfield
Version: 1.0.1
Summary: Drop-in replacement for Django's forms.EmailField. Uses http://mailtest.in to validate email addresses. Caches results.
Home-page: https://github.com/naremit/django-mailtestfield
Author: Jon Combe
Author-email: pypi@joncombe.net
License: BSD licence, see LICENCE file
Platform: UNKNOWN
Classifier: Development Status :: 4 - Beta
Classifier: Environment :: Web Environment
Classifier: Framework :: Django
Classifier: Intended Audience :: Developers
Classifier: License :: OSI Approved :: BSD License
Classifier: Operating System :: OS Independent
Classifier: Natural Language :: English
Classifier: Programming Language :: Python
Classifier: Topic :: Utilities
